teracrafts_huefy_sdk_python/__init__.py
teracrafts_huefy_sdk_python/client.py
teracrafts_huefy_sdk_python/config.py
teracrafts_huefy_sdk_python/exceptions.py
teracrafts_huefy_sdk_python/models.py
teracrafts_huefy_sdk_python/py.typed
teracrafts_huefy_sdk_python-2.0.2.dist-info/METADATA
teracrafts_huefy_sdk_python-2.0.2.dist-info/WHEEL
teracrafts_huefy_sdk_python-2.0.2.dist-info/entry_points.txt
teracrafts_huefy_sdk_python-2.0.2.dist-info/top_level.txt
teracrafts_huefy_sdk_python-2.0.2.dist-info/RECORD
