Metadata-Version: 2.4
Name: teracrafts-huefy-sdk-python
Version: 2.0.2
Summary: Official Python SDK for Huefy - App Mail Templates with dynamic email sending
Home-page: https://github.com/teracrafts/huefy-sdk-python
Author: Huefy Team
Author-email: Huefy Team <hello@huefy.dev>
License: MIT
Project-URL: Documentation, https://docs.huefy.dev/sdk/python
Project-URL: Repository, https://github.com/teracrafts/huefy-sdk-python
Project-URL: Bug Tracker, https://github.com/teracrafts/huefy-sdk-python/issues
Keywords: huefy,email,api,sdk,template,transactional
Classifier: Development Status :: 4 - Beta
Classifier: Intended Audience :: Developers
Classifier: Topic :: Communications :: Email
Classifier: Topic :: Software Development :: Libraries :: Python Modules
Classifier: License :: OSI Approved :: MIT License
Classifier: Programming Language :: Python :: 3
Classifier: Programming Language :: Python :: 3.8
Classifier: Programming Language :: Python :: 3.9
Classifier: Programming Language :: Python :: 3.10
Classifier: Programming Language :: Python :: 3.11
Classifier: Programming Language :: Python :: 3.12
Classifier: Operating System :: OS Independent
Requires-Python: >=3.8
Requires-Dist: requests<3.0.0,>=2.28.0
Requires-Dist: typing-extensions<5.0.0,>=4.0.0; python_version < "3.10"
Requires-Dist: pydantic<3.0.0,>=2.0.0
Provides-Extra: dev
Requires-Dist: pytest>=7.4.0; extra == "dev"
Requires-Dist: pytest-cov>=4.1.0; extra == "dev"
Requires-Dist: pytest-asyncio>=0.21.0; extra == "dev"
Requires-Dist: pytest-mock>=3.11.0; extra == "dev"
Requires-Dist: responses>=0.23.0; extra == "dev"
Requires-Dist: black>=23.0.0; extra == "dev"
Requires-Dist: flake8>=6.0.0; extra == "dev"
Requires-Dist: mypy>=1.4.0; extra == "dev"
Requires-Dist: isort>=5.12.0; extra == "dev"
Requires-Dist: pre-commit>=3.3.0; extra == "dev"
Provides-Extra: async
Requires-Dist: httpx<1.0.0,>=0.24.0; extra == "async"
Requires-Dist: aiohttp<4.0.0,>=3.8.0; extra == "async"
Dynamic: author
Dynamic: home-page
Dynamic: requires-python
